fy_tool_cli/__init__.py
fy_tool_cli/main.py
fy_tool_cli/py.typed
fy_tool_cli-0.5.21.dist-info/LICENSE
fy_tool_cli-0.5.21.dist-info/METADATA
fy_tool_cli-0.5.21.dist-info/WHEEL
fy_tool_cli-0.5.21.dist-info/entry_points.txt
fy_tool_cli-0.5.21.dist-info/RECORD
